raystack/__init__.py
raystack/compat.py
raystack/middlewares.py
raystack/responses.py
raystack/shortcuts.py
raystack/apps/__init__.py
raystack/apps/config.py
raystack/apps/registry.py
raystack/conf/__init__.py
raystack/conf/global_settings.py
raystack/conf/app_template/__init__.py-tpl
raystack/conf/app_template/apps.py-tpl
raystack/conf/app_template/models.py-tpl
raystack/conf/app_template/schemas.py-tpl
raystack/conf/app_template/api/__init__.py-tpl
raystack/conf/app_template/api/resources.py-tpl
raystack/conf/app_template_sync/admin.py-tpl
raystack/conf/project_template/README.md-tpl
raystack/conf/project_template/alembic.ini-tpl
raystack/conf/project_template/manage.py-tpl
raystack/conf/project_template/app/__init__.py-tpl
raystack/conf/project_template/app/apps.py-tpl
raystack/conf/project_template/app/models.py-tpl
raystack/conf/project_template/app/schemas.py-tpl
raystack/conf/project_template/app/api/__init__.py-tpl
raystack/conf/project_template/app/api/items.py-tpl
raystack/conf/project_template/config/settings.py-tpl
raystack/conf/project_template/config/urls.py-tpl
raystack/conf/project_template/core/__init__.py-tpl
raystack/conf/project_template/docs/minimal-api.md-tpl
raystack/conf/project_template/migrations/env.py-tpl
raystack/conf/project_template/migrations/script.py.mako-tpl
raystack/conf/project_template_sync/apps/home/admin.py-tpl
raystack/conf/project_template_sync/config/settings.py-tpl
raystack/conf/project_template_sync/core/__init__.py-tpl
raystack/contrib/openapi.py
raystack/core/__init__.py
raystack/core/asgi.py
raystack/core/exceptions.py
raystack/core/signing.py
raystack/core/validators.py
raystack/core/database/__init__.py
raystack/core/database/base.py
raystack/core/database/manager.py
raystack/core/database/migrations.py
raystack/core/database/models.py
raystack/core/database/query.py
raystack/core/database/settings.py
raystack/core/database/sqlalchemy.py
raystack/core/database/fields/__init__.py
raystack-0.1.5.dist-info/licenses/LICENSE
raystack-0.1.5.dist-info/METADATA
raystack-0.1.5.dist-info/WHEEL
raystack-0.1.5.dist-info/entry_points.txt
raystack-0.1.5.dist-info/top_level.txt
raystack-0.1.5.dist-info/RECORD
