Metadata-Version: 2.4
Name: raystack
Version: 0.1.5
Summary: Starlette sizzles, Django dazzles. The best of both worlds in one framework.
Home-page: https://github.com/ForceFledgling/raystack
Author: Vladimir Penzin
Author-email: Vladimir Penzin <pvenv@icloud.com>
License-Expression: MIT
Project-URL: Homepage, https://github.com/ForceFledgling/raystack
Project-URL: Documentation, https://github.com/ForceFledgling/raystack
Project-URL: Source, https://github.com/ForceFledgling/raystack
Project-URL: Tracker, https://github.com/ForceFledgling/raystack/issues
Classifier: Development Status :: 2 - Pre-Alpha
Classifier: Environment :: Web Environment
Classifier: Framework :: AsyncIO
Classifier: Intended Audience :: Developers
Classifier: Operating System :: OS Independent
Classifier: Programming Language :: Python
Classifier: Programming Language :: Python :: 3
Classifier: Programming Language :: Python :: 3 :: Only
Classifier: Programming Language :: Python :: 3.6
Classifier: Programming Language :: Python :: 3.12
Classifier: Topic :: Internet :: WWW/HTTP
Classifier: Topic :: Internet :: WWW/HTTP :: Dynamic Content
Classifier: Topic :: Software Development :: Libraries :: Application Frameworks
Classifier: Topic :: Software Development :: Libraries :: Python Modules
Requires-Python: >=3.6
License-File: LICENSE
Requires-Dist: uvicorn>=0.15.0
Requires-Dist: starlette>=0.27.0
Requires-Dist: asgiref>=3.0.0
Requires-Dist: python-multipart>=0.0.5
Requires-Dist: sqlalchemy<2.0.0,>=1.4.0
Requires-Dist: alembic>=1.8.0
Requires-Dist: click>=7.0.0
Requires-Dist: sqlmodel>=0.0.8
Requires-Dist: pydantic<2.0.0,>=1.10.13
Dynamic: author
Dynamic: home-page
Dynamic: license-file
Dynamic: requires-python
